{
  "unpublishedCollection": {
    "name": "JSObject1",
    "pageId": "Customer Informaction",
    "pluginId": "js-plugin",
    "pluginType": "JS",
    "actions": [],
    "archivedActions": [],
    "variables": [
      {
        "name": "aggregate",
        "value": "[{\n  \"$match\": {\n    \"status\": \"completed\"\n  }\n}, {\n  \"$count\": \"completedCount\"\n}]"
      }
    ],
    "userPermissions": []
  },
  "id": "Customer Informaction_JSObject1",
  "deleted": false,
  "gitSyncId": "66483d2825a96e6b2e2e8cfe_f99f51d0-eff0-4fe7-a3b3-b17bc3ffb469"
}